py_spring_config/__init__.py
py_spring_config/config.py
py_spring_config/exceptions.py
py_spring_config/loader.py
py_spring_config/tests/__init__.py
py_spring_config/tests/tests.py
py_spring_config-3.60.dist-info/LICENSE
py_spring_config-3.60.dist-info/METADATA
py_spring_config-3.60.dist-info/WHEEL
py_spring_config-3.60.dist-info/top_level.txt
py_spring_config-3.60.dist-info/RECORD
