Metadata-Version: 2.1
Name: py-spring-config
Version: 3.60
Summary: Module for custom Dynaconf loader                 to access a Spring Config server
Home-page: https://github.com/Receptiviti/py_spring_config
Author: Tanya Whyte & Lucas Sant' Anna
Author-email: twhyte@receptiviti.com
License: Receptiviti Inc.
Keywords: python spring cloud config
Platform: UNKNOWN
Classifier: Development Status :: 3 - Alpha
Classifier: Programming Language :: Python :: 3.5
Requires-Dist: requests
Requires-Dist: dynaconf
